build/lib/requestez/__init__.py
build/lib/requestez/asynchronous/__init__.py
build/lib/requestez/encryption/__init__.py
build/lib/requestez/encryption/dejuice.py
build/lib/requestez/encryption/unpack.py
build/lib/requestez/helpers/__init__.py
build/lib/requestez/helpers/logger.py
build/lib/requestez/helpers/merge.py
build/lib/requestez/helpers/progress_bar.py
build/lib/requestez/parsers/__init__.py
build/lib/requestez/services/__init__.py
build/lib/requestez/services/cache/__init__.py
build/lib/test/requestez_logging.py
requestez/__init__.py
requestez/asynchronous/__init__.py
requestez/encryption/__init__.py
requestez/encryption/dejuice.py
requestez/encryption/unpack.py
requestez/helpers/__init__.py
requestez/helpers/logger.py
requestez/helpers/merge.py
requestez/helpers/progress_bar.py
requestez/parsers/__init__.py
requestez/services/__init__.py
requestez/services/cache/__init__.py
requestez-0.1.9.dist-info/licenses/LICENSE.txt
test/requestez_logging.py
requestez-0.1.9.dist-info/METADATA
requestez-0.1.9.dist-info/WHEEL
requestez-0.1.9.dist-info/top_level.txt
requestez-0.1.9.dist-info/RECORD
